pyappsetup/__init__.py
pyappsetup/const.py
pyappsetup/datatypes.py
pyappsetup/interface.py
pyappsetup/parser.py
pyappsetup/structure.py
pyappsetup/writer.py
pyappsetup-1.0.0.dist-info/LICENSE
pyappsetup-1.0.0.dist-info/METADATA
pyappsetup-1.0.0.dist-info/WHEEL
pyappsetup-1.0.0.dist-info/top_level.txt
pyappsetup-1.0.0.dist-info/RECORD
