Metadata-Version: 2.1
Name: pyappsetup
Version: 1.0.0
Summary: Reading / writing configuration files
Home-page: https://github.com/louisdevie/pyappsetup
Author: Louis DEVIE
Author-email: louisdevie.contact@gmail.com
License: UNKNOWN
Platform: UNKNOWN
Classifier: Programming Language :: Python :: 3
Classifier: License :: OSI Approved :: MIT License
Classifier: Operating System :: POSIX :: Linux
Requires-Python: >=3.8
